Metadata-Version: 2.1
Name: voidsafe
Version: 0.2.0
Summary: A null-safe-like approach to Python programming language.
Home-page: https://github.com/gus-caribe/voidsafe
Author: Gustavo Cardoso Ribeiro
Author-email: gustavocaribe@caribesphaneron.com
License: MIT
Keywords: voidsafe,nullsafe,none-aware,python
Classifier: Development Status :: 4 - Beta
Classifier: Programming Language :: Python :: 3.11
Classifier: Environment :: Plugins
Classifier: Intended Audience :: Developers
Classifier: License :: OSI Approved :: MIT License
Classifier: Natural Language :: English
Classifier: Operating System :: OS Independent
Classifier: Topic :: Software Development :: Libraries :: Python Modules
Classifier: Topic :: Utilities
Classifier: Typing :: Typed
License-File: LICENSE
